[
  {
    "Album": "After Dark",
    "Album Artist": "Aimer",
    "Artist": "Aimer",
    "Copyright": "℗ 2013 SME Records",
    "Date": 2013,
    "Disc Number": "1/1",
    "Genre": "J-Pop",
    "Title": "After Dark -prologue-",
    "Track Number": "1/12"
  },
  {
    "Album": "After Dark",
    "Album Artist": "Aimer",
    "Artist": "Aimer",
    "Copyright": "℗ 2013 SME Records",
    "Date": 2013,
    "Disc Number": "1/1",
    "Genre": "J-Pop",
    "Title": "Polaris",
    "Track Number": "2/12"
  },
  {
    "Album": "After Dark",
    "Album Artist": "Aimer",
    "Artist": "Aimer",
    "Copyright": "℗ 2013 SME Records",
    "Date": 2013,
    "Disc Number": "1/1",
    "Genre": "J-Pop",
    "Title": "words",
    "Track Number": "3/12"
  },
  {
    "Album": "After Dark",
    "Album Artist": "Aimer",
    "Artist": "Aimer",
    "Copyright": "℗ 2013 SME Records",
    "Date": 2013,
    "Disc Number": "1/1",
    "Genre": "J-Pop",
    "Title": "AM02:00 (haruka nakamura La Nuit remix)",
    "Track Number": "4/12"
  },
  {
    "Album": "After Dark",
    "Album Artist": "Aimer",
    "Artist": "Aimer",
    "Copyright": "℗ 2013 SME Records",
    "Date": 2013,
    "Disc Number": "1/1",
    "Genre": "J-Pop",
    "Title": "After Rain",
    "Track Number": "5/12"
  },
  {
    "Album": "After Dark",
    "Album Artist": "Aimer",
    "Artist": "Aimer",
    "Copyright": "℗ 2013 SME Records",
    "Date": 2013,
    "Disc Number": "1/1",
    "Genre": "J-Pop",
    "Title": "Amazing Grace -Live in church ver.-",
    "Track Number": "6/12"
  },
  {
    "Album": "After Dark",
    "Album Artist": "Aimer",
    "Artist": "Aimer",
    "Copyright": "℗ 2013 SME Records",
    "Date": 2013,
    "Disc Number": "1/1",
    "Genre": "J-Pop",
    "Title": "Anata Ni Deawanakereba ~Kasetsutouka~ -Live in church ver.-",
    "Track Number": "7/12"
  },
  {
    "Album": "After Dark",
    "Album Artist": "Aimer",
    "Artist": "Aimer",
    "Copyright": "℗ 2013 SME Records",
    "Date": 2013,
    "Disc Number": "1/1",
    "Genre": "J-Pop",
    "Title": "Kyou Kara Omoide -Live in church ver.-",
    "Track Number": "8/12"
  },
  {
    "Album": "After Dark",
    "Album Artist": "Aimer",
    "Artist": "Aimer",
    "Copyright": "℗ 2013 SME Records",
    "Date": 2013,
    "Disc Number": "1/1",
    "Genre": "J-Pop",
    "Title": "Hoshikuzu Venus -Live in church ver.-",
    "Track Number": "9/12"
  },
  {
    "Album": "After Dark",
    "Album Artist": "Aimer",
    "Artist": "Aimer",
    "Copyright": "℗ 2013 SME Records",
    "Date": 2013,
    "Disc Number": "1/1",
    "Genre": "J-Pop",
    "Title": "Samishikute Nemurenai Yoru Wa -Live in church ver.-",
    "Track Number": "10/12"
  },
  {
    "Album": "After Dark",
    "Album Artist": "Aimer",
    "Artist": "Aimer",
    "Copyright": "℗ 2013 SME Records",
    "Date": 2013,
    "Disc Number": "1/1",
    "Genre": "J-Pop",
    "Title": "RE:I AM -Live in church ver.-",
    "Track Number": "11/12"
  },
  {
    "Album": "After Dark",
    "Album Artist": "Aimer",
    "Artist": "Aimer",
    "Copyright": "℗ 2013 SME Records",
    "Date": 2013,
    "Disc Number": "1/1",
    "Genre": "J-Pop",
    "Title": "Rokutousei No Yoru -from Live at anywhere-",
    "Track Number": "12/12"
  },
  {
    "Album": "Akane Sasu / everlasting snow",
    "Album Artist": "Aimer",
    "Artist": "Aimer with Takahito Uchisawa",
    "Copyright": "℗ 2016 SME Records",
    "Date": 2016,
    "Disc Number": "1/1",
    "Genre": "J-Pop",
    "Title": "Kataomoi 5th Anniversary Live ver.",
    "Track Number": "1/1"
  },
  {
    "Album": "BEST SELECTION \"blanc",
    "Album Artist": "Aimer",
    "Artist": "Aimer",
    "Copyright": "℗ 2016 SME Records",
    "Date": 2017,
    "Disc Number": "1/1",
    "Genre": "J-Pop",
    "Title": "Akane Sasu",
    "Track Number": "1/2"
  },
  {
    "Album": "BEST SELECTION \"blanc",
    "Album Artist": "Aimer",
    "Artist": "Aimer",
    "Copyright": "℗ 2016 SME Records",
    "Date": 2017,
    "Disc Number": "1/1",
    "Genre": "J-Pop",
    "Title": "everlasting snow",
    "Track Number": "2/2"
  },
  {
    "Album": "BEST SELECTION \"noir",
    "Album Artist": "Aimer",
    "Artist": "Aimer",
    "Copyright": "℗ 2014 Defstar Records",
    "Date": 2017,
    "Disc Number": "1/1",
    "Genre": "J-Pop",
    "Title": "holLow wORlD",
    "Track Number": "1/1"
  },
  {
    "Album": "Black Bird / Tiny Dancers / Omoide Wa Kirei De",
    "Album Artist": "Aimer",
    "Artist": "Aimer",
    "Copyright": "℗ 2018 Sony Music Entertainment (Japan) Inc.",
    "Date": 2018,
    "Disc Number": "1/1",
    "Genre": "J-Pop",
    "Title": "Tiny Dancers",
    "Track Number": "1/2"
  },
  {
    "Album": "Black Bird / Tiny Dancers / Omoide Wa Kirei De",
    "Album Artist": "Aimer",
    "Artist": "Aimer",
    "Copyright": "℗ 2018 Sony Music Entertainment (Japan) Inc.",
    "Date": 2018,
    "Disc Number": "1/1",
    "Genre": "J-Pop",
    "Title": "Kyou Kara Omoide Evergreen ver.",
    "Track Number": "2/2"
  },
  {
    "Album": "Brave Shine",
    "Album Artist": "Aimer",
    "Artist": "Aimer",
    "Copyright": "℗ 2015 Defstar Records",
    "Date": 2015,
    "Disc Number": "1/1",
    "Genre": "J-Pop",
    "Title": "Ophelia",
    "Track Number": "1/4"
  },
  {
    "Album": "Brave Shine",
    "Album Artist": "Aimer",
    "Artist": "Aimer",
    "Copyright": "℗ 2015 Defstar Records",
    "Date": 2015,
    "Disc Number": "1/1",
    "Genre": "J-Pop",
    "Title": "Kimi Wo Matsu -acoustic ver.-",
    "Track Number": "2/4"
  },
  {
    "Album": "Brave Shine",
    "Album Artist": "Aimer",
    "Artist": "Aimer",
    "Copyright": "℗ 2015 Defstar Records",
    "Date": 2015,
    "Disc Number": "1/1",
    "Genre": "J-Pop",
    "Title": "AM03:00 (Live \"Midnight Sun\" ver.)",
    "Track Number": "3/4"
  },
  {
    "Album": "Brave Shine",
    "Album Artist": "Aimer",
    "Artist": "Aimer",
    "Copyright": "℗ 2015 Defstar Records",
    "Date": 2015,
    "Disc Number": "1/1",
    "Genre": "J-Pop",
    "Title": "Shichigatsu No Tsubasa (Live \"Midnight Sun\" ver.)",
    "Track Number": "4/4"
  },
  {
    "Album": "broKen NIGHT / holLow wORlD",
    "Album Artist": "Aimer",
    "Artist": "Aimer",
    "Copyright": "℗ 2014 Defstar Records",
    "Date": 2014,
    "Disc Number": "1/1",
    "Genre": "J-Pop",
    "Title": "my sweetest one",
    "Track Number": "1/1"
  },
  {
    "Album": "Chouchou Musubi",
    "Album Artist": "Aimer",
    "Artist": "Aimer",
    "Copyright": "℗ 2016 SME Records",
    "Date": 2016,
    "Disc Number": "1/1",
    "Genre": "J-Pop",
    "Title": "Natsukusa Ni Kimi Wo Omou",
    "Track Number": "1/2"
  },
  {
    "Album": "Chouchou Musubi",
    "Album Artist": "Aimer",
    "Artist": "Aimer",
    "Copyright": "℗ 2016 SME Records",
    "Date": 2016,
    "Disc Number": "1/1",
    "Genre": "J-Pop",
    "Title": "September San",
    "Track Number": "2/2"
  },
  {
    "Album": "Dareka, Umi Wo.",
    "Album Artist": "Aimer",
    "Artist": "Aimer",
    "Copyright": "℗ 2014 SME Records",
    "Date": 2014,
    "Disc Number": "1/1",
    "Genre": "J-Pop",
    "Title": "Hakuchuumu",
    "Track Number": "1/1"
  },
  {
    "Album": "DAWN",
    "Album Artist": "Aimer",
    "Artist": "Aimer",
    "Copyright": "℗ 2014(4.8), 2015(1-3.5-7.9-13) DefSTAR RECORDS",
    "Date": 2015,
    "Disc Number": "1/1",
    "Genre": "J-Pop",
    "Title": "MOON RIVER -prologue-",
    "Track Number": "1/13"
  },
  {
    "Album": "DAWN",
    "Album Artist": "Aimer",
    "Artist": "Aimer",
    "Copyright": "℗ 2014(4.8), 2015(1-3.5-7.9-13) DefSTAR RECORDS",
    "Date": 2015,
    "Disc Number": "1/1",
    "Genre": "J-Pop",
    "Title": "Believe Be:leave",
    "Track Number": "2/13"
  },
  {
    "Album": "DAWN",
    "Album Artist": "Aimer",
    "Artist": "Aimer",
    "Copyright": "℗ 2014(4.8), 2015(1-3.5-7.9-13) DefSTAR RECORDS",
    "Date": 2015,
    "Disc Number": "1/1",
    "Genre": "J-Pop",
    "Title": "Kimi Wo Matsu",
    "Track Number": "3/13"
  },
  {
    "Album": "DAWN",
    "Album Artist": "Aimer",
    "Artist": "Aimer",
    "Copyright": "℗ 2014(4.8), 2015(1-3.5-7.9-13) DefSTAR RECORDS",
    "Date": 2015,
    "Disc Number": "1/1",
    "Genre": "J-Pop",
    "Title": "broKen NIGHT",
    "Track Number": "4/13"
  },
  {
    "Album": "DAWN",
    "Album Artist": "Aimer",
    "Artist": "Aimer",
    "Copyright": "℗ 2014(4.8), 2015(1-3.5-7.9-13) DefSTAR RECORDS",
    "Date": 2015,
    "Disc Number": "1/1",
    "Genre": "J-Pop",
    "Title": "Noir! Noir!",
    "Track Number": "5/13"
  },
  {
    "Album": "DAWN",
    "Album Artist": "Aimer",
    "Artist": "Aimer",
    "Copyright": "℗ 2014(4.8), 2015(1-3.5-7.9-13) DefSTAR RECORDS",
    "Date": 2015,
    "Disc Number": "1/1",
    "Genre": "J-Pop",
    "Title": "Re:far",
    "Track Number": "6/13"
  },
  {
    "Album": "DAWN",
    "Album Artist": "Aimer",
    "Artist": "Aimer",
    "Copyright": "℗ 2014(4.8), 2015(1-3.5-7.9-13) DefSTAR RECORDS",
    "Date": 2015,
    "Disc Number": "1/1",
    "Genre": "J-Pop",
    "Title": "AM04:00",
    "Track Number": "7/13"
  },
  {
    "Album": "DAWN",
    "Album Artist": "Aimer",
    "Artist": "Aimer",
    "Copyright": "℗ 2014(4.8), 2015(1-3.5-7.9-13) DefSTAR RECORDS",
    "Date": 2015,
    "Disc Number": "1/1",
    "Genre": "J-Pop",
    "Title": "Dareka, Umi Wo.",
    "Track Number": "8/13"
  },
  {
    "Album": "DAWN",
    "Album Artist": "Aimer",
    "Artist": "Aimer",
    "Copyright": "℗ 2014(4.8), 2015(1-3.5-7.9-13) DefSTAR RECORDS",
    "Date": 2015,
    "Disc Number": "1/1",
    "Genre": "J-Pop",
    "Title": "LAST STARDUST",
    "Track Number": "9/13"
  },
  {
    "Album": "DAWN",
    "Album Artist": "Aimer",
    "Artist": "Aimer",
    "Copyright": "℗ 2014(4.8), 2015(1-3.5-7.9-13) DefSTAR RECORDS",
    "Date": 2015,
    "Disc Number": "1/1",
    "Genre": "J-Pop",
    "Title": "Brave Shine",
    "Track Number": "10/13"
  },
  {
    "Album": "DAWN",
    "Album Artist": "Aimer",
    "Artist": "Aimer",
    "Copyright": "℗ 2014(4.8), 2015(1-3.5-7.9-13) DefSTAR RECORDS",
    "Date": 2015,
    "Disc Number": "1/1",
    "Genre": "J-Pop",
    "Title": "Kizuna",
    "Track Number": "11/13"
  },
  {
    "Album": "DAWN",
    "Album Artist": "Aimer",
    "Artist": "Aimer",
    "Copyright": "℗ 2014(4.8), 2015(1-3.5-7.9-13) DefSTAR RECORDS",
    "Date": 2015,
    "Disc Number": "1/1",
    "Genre": "J-Pop",
    "Title": "DAWN",
    "Track Number": "12/13"
  },
  {
    "Album": "DAWN",
    "Album Artist": "Aimer",
    "Artist": "Aimer",
    "Copyright": "℗ 2014(4.8), 2015(1-3.5-7.9-13) DefSTAR RECORDS",
    "Date": 2015,
    "Disc Number": "1/1",
    "Genre": "J-Pop",
    "Title": "MOON RIVER",
    "Track Number": "13/13"
  },
  {
    "Album": "daydream",
    "Album Artist": "Aimer",
    "Artist": "Aimer with Taka",
    "Copyright": "℗ 2014(5), 2016(1-4,6-13) SME Records",
    "Date": 2016,
    "Disc Number": "1/1",
    "Genre": "J-Pop",
    "Title": "insane dream",
    "Track Number": "1/13"
  },
  {
    "Album": "daydream",
    "Album Artist": "Aimer",
    "Artist": "Aimer with chelly",
    "Copyright": "℗ 2014(5), 2016(1-4,6-13) SME Records",
    "Date": 2016,
    "Disc Number": "1/1",
    "Genre": "J-Pop",
    "Title": "ninelie",
    "Track Number": "2/13"
  },
  {
    "Album": "daydream",
    "Album Artist": "Aimer",
    "Artist": "Aimer",
    "Copyright": "℗ 2014(5), 2016(1-4,6-13) SME Records",
    "Date": 2016,
    "Disc Number": "1/1",
    "Genre": "J-Pop",
    "Title": "twoface",
    "Track Number": "3/13"
  },
  {
    "Album": "daydream",
    "Album Artist": "Aimer",
    "Artist": "Aimer",
    "Copyright": "℗ 2014(5), 2016(1-4,6-13) SME Records",
    "Date": 2016,
    "Disc Number": "1/1",
    "Genre": "J-Pop",
    "Title": "Higher Ground",
    "Track Number": "4/13"
  },
  {
    "Album": "daydream",
    "Album Artist": "Aimer",
    "Artist": "Aimer with Mao Abe",
    "Copyright": "℗ 2014(5), 2016(1-4,6-13) SME Records",
    "Date": 2016,
    "Disc Number": "1/1",
    "Genre": "J-Pop",
    "Title": "for Lonely",
    "Track Number": "5/13"
  },
  {
    "Album": "daydream",
    "Album Artist": "Aimer",
    "Artist": "Aimer with Yojiro Noda",
    "Copyright": "℗ 2014(5), 2016(1-4,6-13) SME Records",
    "Date": 2016,
    "Disc Number": "1/1",
    "Genre": "J-Pop",
    "Title": "Chouchou Musubi",
    "Track Number": "6/13"
  },
  {
    "Album": "daydream",
    "Album Artist": "Aimer",
    "Artist": "Aimer",
    "Copyright": "℗ 2014(5), 2016(1-4,6-13) SME Records",
    "Date": 2016,
    "Disc Number": "1/1",
    "Genre": "J-Pop",
    "Title": "Kataomoi",
    "Track Number": "7/13"
  },
  {
    "Album": "daydream",
    "Album Artist": "Aimer",
    "Artist": "Aimer",
    "Copyright": "℗ 2014(5), 2016(1-4,6-13) SME Records",
    "Date": 2016,
    "Disc Number": "1/1",
    "Genre": "J-Pop",
    "Title": "Hƶ",
    "Track Number": "8/13"
  },
  {
    "Album": "daydream",
    "Album Artist": "Aimer",
    "Artist": "Aimer",
    "Copyright": "℗ 2014(5), 2016(1-4,6-13) SME Records",
    "Date": 2016,
    "Disc Number": "1/1",
    "Genre": "J-Pop",
    "Title": "Kowairo",
    "Track Number": "9/13"
  },
  {
    "Album": "daydream",
    "Album Artist": "Aimer",
    "Artist": "Aimer",
    "Copyright": "℗ 2014(5), 2016(1-4,6-13) SME Records",
    "Date": 2016,
    "Disc Number": "1/1",
    "Genre": "J-Pop",
    "Title": "closer",
    "Track Number": "10/13"
  },
  {
    "Album": "daydream",
    "Album Artist": "Aimer",
    "Artist": "Aimer",
    "Copyright": "℗ 2014(5), 2016(1-4,6-13) SME Records",
    "Date": 2016,
    "Disc Number": "1/1",
    "Genre": "J-Pop",
    "Title": "Falling Alone",
    "Track Number": "11/13"
  },
  {
    "Album": "daydream",
    "Album Artist": "Aimer",
    "Artist": "Aimer",
    "Copyright": "℗ 2014(5), 2016(1-4,6-13) SME Records",
    "Date": 2016,
    "Disc Number": "1/1",
    "Genre": "J-Pop",
    "Title": "us",
    "Track Number": "12/13"
  },
  {
    "Album": "daydream",
    "Album Artist": "Aimer",
    "Artist": "Aimer",
    "Copyright": "℗ 2014(5), 2016(1-4,6-13) SME Records",
    "Date": 2016,
    "Disc Number": "1/1",
    "Genre": "J-Pop",
    "Title": "Stars in the rain",
    "Track Number": "13/13"
  },
  {
    "Album": "Haru Wa Yuku / marie",
    "Album Artist": "Aimer",
    "Artist": "Aimer",
    "Copyright": "℗ 2020 Sony Music Labels Inc.",
    "Date": 2020,
    "Disc Number": "1/1",
    "Genre": "J-Pop",
    "Title": "Run Riot",
    "Track Number": "1/2"
  },
  {
    "Album": "Haru Wa Yuku / marie",
    "Album Artist": "Aimer",
    "Artist": "Aimer",
    "Copyright": "℗ 2020 Sony Music Labels Inc.",
    "Date": 2020,
    "Disc Number": "1/1",
    "Genre": "J-Pop",
    "Title": "Hana No Uta end of spring ver.",
    "Track Number": "2/2"
  },
  {
    "Album": "I beg you / Hanabiratachi No March / Sailing",
    "Album Artist": "Aimer",
    "Artist": "Aimer",
    "Copyright": "℗ 2019 SME Records",
    "Date": 2019,
    "Disc Number": "1/1",
    "Genre": "J-Pop",
    "Title": "Mine -Mellow Yellow ver.-",
    "Track Number": "1/1"
  },
  {
    "Album": "insane dream / us",
    "Album Artist": "Aimer",
    "Artist": "Aimer",
    "Copyright": "℗ 2016 SME Records",
    "Date": 2016,
    "Disc Number": "1/1",
    "Genre": "J-Pop",
    "Title": "tone",
    "Track Number": "1/1"
  },
  {
    "Album": "Kogoesou Na Kisetsu Kara",
    "Album Artist": "Aimer",
    "Artist": "Aimer",
    "Copyright": "℗ 2017 SME Records",
    "Date": 2017,
    "Disc Number": "1/1",
    "Genre": "J-Pop",
    "Title": "Kogoesou Na Kisetsu Kara",
    "Track Number": "1/1"
  },
  {
    "Album": "Midnight Sun",
    "Album Artist": "Aimer",
    "Artist": "Aimer",
    "Copyright": "℗ 2013(2.4.9) 2014(1.3.5-810-13 Defstar Records",
    "Date": 2014,
    "Disc Number": "1/1",
    "Genre": "J-Pop",
    "Title": "WHEN YOU WISH UPON A STAR -prologue-",
    "Track Number": "1/13"
  },
  {
    "Album": "Midnight Sun",
    "Album Artist": "Aimer",
    "Artist": "Aimer",
    "Copyright": "℗ 2013(2.4.9) 2014(1.3.5-810-13 Defstar Records",
    "Date": 2014,
    "Disc Number": "1/1",
    "Genre": "J-Pop",
    "Title": "Nemuri No Mori",
    "Track Number": "2/13"
  },
  {
    "Album": "Midnight Sun",
    "Album Artist": "Aimer",
    "Artist": "Aimer",
    "Copyright": "℗ 2013(2.4.9) 2014(1.3.5-810-13 Defstar Records",
    "Date": 2014,
    "Disc Number": "1/1",
    "Genre": "J-Pop",
    "Title": "Shichigatsu No Tsubasa",
    "Track Number": "3/13"
  },
  {
    "Album": "Midnight Sun",
    "Album Artist": "Aimer",
    "Artist": "Aimer",
    "Copyright": "℗ 2013(2.4.9) 2014(1.3.5-810-13 Defstar Records",
    "Date": 2014,
    "Disc Number": "1/1",
    "Genre": "J-Pop",
    "Title": "words",
    "Track Number": "4/13"
  },
  {
    "Album": "Midnight Sun",
    "Album Artist": "Aimer",
    "Artist": "Aimer",
    "Copyright": "℗ 2013(2.4.9) 2014(1.3.5-810-13 Defstar Records",
    "Date": 2014,
    "Disc Number": "1/1",
    "Genre": "J-Pop",
    "Title": "Cold Sun",
    "Track Number": "5/13"
  },
  {
    "Album": "Midnight Sun",
    "Album Artist": "Aimer",
    "Artist": "Aimer",
    "Copyright": "℗ 2013(2.4.9) 2014(1.3.5-810-13 Defstar Records",
    "Date": 2014,
    "Disc Number": "1/1",
    "Genre": "J-Pop",
    "Title": "AM03:00",
    "Track Number": "6/13"
  },
  {
    "Album": "Midnight Sun",
    "Album Artist": "Aimer",
    "Artist": "Aimer",
    "Copyright": "℗ 2013(2.4.9) 2014(1.3.5-810-13 Defstar Records",
    "Date": 2014,
    "Disc Number": "1/1",
    "Genre": "J-Pop",
    "Title": "Chiisana Hoshi No Melody",
    "Track Number": "7/13"
  },
  {
    "Album": "Midnight Sun",
    "Album Artist": "Aimer",
    "Artist": "Aimer",
    "Copyright": "℗ 2013(2.4.9) 2014(1.3.5-810-13 Defstar Records",
    "Date": 2014,
    "Disc Number": "1/1",
    "Genre": "J-Pop",
    "Title": "VOICE",
    "Track Number": "8/13"
  },
  {
    "Album": "Midnight Sun",
    "Album Artist": "Aimer",
    "Artist": "Aimer",
    "Copyright": "℗ 2013(2.4.9) 2014(1.3.5-810-13 Defstar Records",
    "Date": 2014,
    "Disc Number": "1/1",
    "Genre": "J-Pop",
    "Title": "RE:I AM",
    "Track Number": "9/13"
  },
  {
    "Album": "Midnight Sun",
    "Album Artist": "Aimer",
    "Artist": "Aimer",
    "Copyright": "℗ 2013(2.4.9) 2014(1.3.5-810-13 Defstar Records",
    "Date": 2014,
    "Disc Number": "1/1",
    "Genre": "J-Pop",
    "Title": "StarRingChild",
    "Track Number": "10/13"
  },
  {
    "Album": "Midnight Sun",
    "Album Artist": "Aimer",
    "Artist": "Aimer",
    "Copyright": "℗ 2013(2.4.9) 2014(1.3.5-810-13 Defstar Records",
    "Date": 2014,
    "Disc Number": "1/1",
    "Genre": "J-Pop",
    "Title": "Hoshi No Kieta Yoru Ni (Re-echoed by Genki Rockets × give me wallets)",
    "Track Number": "11/13"
  },
  {
    "Album": "Midnight Sun",
    "Album Artist": "Aimer",
    "Artist": "Aimer",
    "Copyright": "℗ 2013(2.4.9) 2014(1.3.5-810-13 Defstar Records",
    "Date": 2014,
    "Disc Number": "1/1",
    "Genre": "J-Pop",
    "Title": "Iris",
    "Track Number": "12/13"
  },
  {
    "Album": "Midnight Sun",
    "Album Artist": "Aimer",
    "Artist": "Aimer",
    "Copyright": "℗ 2013(2.4.9) 2014(1.3.5-810-13 Defstar Records",
    "Date": 2014,
    "Disc Number": "1/1",
    "Genre": "J-Pop",
    "Title": "WHEN YOU WISH UPON A STAR",
    "Track Number": "13/13"
  },
  {
    "Album": "Penny Rain",
    "Album Artist": "Aimer",
    "Artist": "Aimer",
    "Copyright": "℗ 2017(9), 2018(3,5,7), 2019(1,2,4,6,8,10) SME Records",
    "Date": 2019,
    "Disc Number": "1/1",
    "Genre": "J-Pop",
    "Title": "pluie",
    "Track Number": "1/10"
  },
  {
    "Album": "Penny Rain",
    "Album Artist": "Aimer",
    "Artist": "Aimer",
    "Copyright": "℗ 2017(9), 2018(3,5,7), 2019(1,2,4,6,8,10) SME Records",
    "Date": 2019,
    "Disc Number": "1/1",
    "Genre": "J-Pop",
    "Title": "I beg you",
    "Track Number": "2/10"
  },
  {
    "Album": "Penny Rain",
    "Album Artist": "Aimer",
    "Artist": "Aimer",
    "Copyright": "℗ 2017(9), 2018(3,5,7), 2019(1,2,4,6,8,10) SME Records",
    "Date": 2019,
    "Disc Number": "1/1",
    "Genre": "J-Pop",
    "Title": "Black Bird",
    "Track Number": "3/10"
  },
  {
    "Album": "Penny Rain",
    "Album Artist": "Aimer",
    "Artist": "Aimer",
    "Copyright": "℗ 2017(9), 2018(3,5,7), 2019(1,2,4,6,8,10) SME Records",
    "Date": 2019,
    "Disc Number": "1/1",
    "Genre": "J-Pop",
    "Title": "Sailing",
    "Track Number": "4/10"
  },
  {
    "Album": "Penny Rain",
    "Album Artist": "Aimer",
    "Artist": "Aimer",
    "Copyright": "℗ 2017(9), 2018(3,5,7), 2019(1,2,4,6,8,10) SME Records",
    "Date": 2019,
    "Disc Number": "1/1",
    "Genre": "J-Pop",
    "Title": "Mabayui Bakari",
    "Track Number": "5/10"
  },
  {
    "Album": "Penny Rain",
    "Album Artist": "Aimer",
    "Artist": "Aimer",
    "Copyright": "℗ 2017(9), 2018(3,5,7), 2019(1,2,4,6,8,10) SME Records",
    "Date": 2019,
    "Disc Number": "1/1",
    "Genre": "J-Pop",
    "Title": "Stand By You",
    "Track Number": "6/10"
  },
  {
    "Album": "Penny Rain",
    "Album Artist": "Aimer",
    "Artist": "Aimer",
    "Copyright": "℗ 2017(9), 2018(3,5,7), 2019(1,2,4,6,8,10) SME Records",
    "Date": 2019,
    "Disc Number": "1/1",
    "Genre": "J-Pop",
    "Title": "Ref:rain",
    "Track Number": "7/10"
  },
  {
    "Album": "Penny Rain",
    "Album Artist": "Aimer",
    "Artist": "Aimer",
    "Copyright": "℗ 2017(9), 2018(3,5,7), 2019(1,2,4,6,8,10) SME Records",
    "Date": 2019,
    "Disc Number": "1/1",
    "Genre": "J-Pop",
    "Title": "i-mage〈in/AR〉",
    "Track Number": "8/10"
  },
  {
    "Album": "Penny Rain",
    "Album Artist": "Aimer",
    "Artist": "Aimer",
    "Copyright": "℗ 2017(9), 2018(3,5,7), 2019(1,2,4,6,8,10) SME Records",
    "Date": 2019,
    "Disc Number": "1/1",
    "Genre": "J-Pop",
    "Title": "Hana No Uta",
    "Track Number": "9/10"
  },
  {
    "Album": "Penny Rain",
    "Album Artist": "Aimer",
    "Artist": "Aimer",
    "Copyright": "℗ 2017(9), 2018(3,5,7), 2019(1,2,4,6,8,10) SME Records",
    "Date": 2019,
    "Disc Number": "1/1",
    "Genre": "J-Pop",
    "Title": "April Showers",
    "Track Number": "10/10"
  },
  {
    "Album": "RE:I AM",
    "Album Artist": "Aimer",
    "Artist": "Aimer",
    "Copyright": "℗ 2013 SME Records",
    "Date": 2013,
    "Disc Number": "1/1",
    "Genre": "J-Pop",
    "Title": "Kyou Kara Omoide",
    "Track Number": "1/1"
  },
  {
    "Album": "Sleepless Nights",
    "Album Artist": "Aimer",
    "Artist": "Aimer",
    "Copyright": "℗ 2012 Sony Music Entertainment (Japan) Inc.",
    "Date": 2012,
    "Disc Number": "1/1",
    "Genre": "J-Pop",
    "Title": "TWINKLE TWINKLE LITTLE STAR -prologue-",
    "Track Number": "1/13"
  },
  {
    "Album": "Sleepless Nights",
    "Album Artist": "Aimer",
    "Artist": "Aimer",
    "Copyright": "℗ 2012 Sony Music Entertainment (Japan) Inc.",
    "Date": 2012,
    "Disc Number": "1/1",
    "Genre": "J-Pop",
    "Title": "Yakou Ressha ~nothing to lose~",
    "Track Number": "2/13"
  },
  {
    "Album": "Sleepless Nights",
    "Album Artist": "Aimer",
    "Artist": "Aimer",
    "Copyright": "℗ 2012 Sony Music Entertainment (Japan) Inc.",
    "Date": 2012,
    "Disc Number": "1/1",
    "Genre": "J-Pop",
    "Title": "Anata Ni Deawanakereba ~Kasetsutouka~",
    "Track Number": "3/13"
  },
  {
    "Album": "Sleepless Nights",
    "Album Artist": "Aimer",
    "Artist": "Aimer",
    "Copyright": "℗ 2012 Sony Music Entertainment (Japan) Inc.",
    "Date": 2012,
    "Disc Number": "1/1",
    "Genre": "J-Pop",
    "Title": "Egao",
    "Track Number": "4/13"
  },
  {
    "Album": "Sleepless Nights",
    "Album Artist": "Aimer",
    "Artist": "Aimer",
    "Copyright": "℗ 2012 Sony Music Entertainment (Japan) Inc.",
    "Date": 2012,
    "Disc Number": "1/1",
    "Genre": "J-Pop",
    "Title": "Re:pray",
    "Track Number": "5/13"
  },
  {
    "Album": "Sleepless Nights",
    "Album Artist": "Aimer",
    "Artist": "Aimer",
    "Copyright": "℗ 2012 Sony Music Entertainment (Japan) Inc.",
    "Date": 2012,
    "Disc Number": "1/1",
    "Genre": "J-Pop",
    "Title": "Kanashimi Wa Aurora Ni (Restarred by Takagi Masakatsu)",
    "Track Number": "6/13"
  },
  {
    "Album": "Sleepless Nights",
    "Album Artist": "Aimer",
    "Artist": "Aimer",
    "Copyright": "℗ 2012 Sony Music Entertainment (Japan) Inc.",
    "Date": 2012,
    "Disc Number": "1/1",
    "Genre": "J-Pop",
    "Title": "Samishikute Nemurenai Yoru Wa",
    "Track Number": "7/13"
  },
  {
    "Album": "Sleepless Nights",
    "Album Artist": "Aimer",
    "Artist": "Aimer",
    "Copyright": "℗ 2012 Sony Music Entertainment (Japan) Inc.",
    "Date": 2012,
    "Disc Number": "1/1",
    "Genre": "J-Pop",
    "Title": "AM02:00",
    "Track Number": "8/13"
  },
  {
    "Album": "Sleepless Nights",
    "Album Artist": "Aimer",
    "Artist": "Aimer",
    "Copyright": "℗ 2012 Sony Music Entertainment (Japan) Inc.",
    "Date": 2012,
    "Disc Number": "1/1",
    "Genre": "J-Pop",
    "Title": "Hoshikuzu Venus",
    "Track Number": "9/13"
  },
  {
    "Album": "Sleepless Nights",
    "Album Artist": "Aimer",
    "Artist": "Aimer",
    "Copyright": "℗ 2012 Sony Music Entertainment (Japan) Inc.",
    "Date": 2012,
    "Disc Number": "1/1",
    "Genre": "J-Pop",
    "Title": "Yuki No Furu Machi",
    "Track Number": "10/13"
  },
  {
    "Album": "Sleepless Nights",
    "Album Artist": "Aimer",
    "Artist": "Aimer",
    "Copyright": "℗ 2012 Sony Music Entertainment (Japan) Inc.",
    "Date": 2012,
    "Disc Number": "1/1",
    "Genre": "J-Pop",
    "Title": "Fuyu No Diamond (Re-echoed by Genki Rockets)",
    "Track Number": "11/13"
  },
  {
    "Album": "Sleepless Nights",
    "Album Artist": "Aimer",
    "Artist": "Aimer",
    "Copyright": "℗ 2012 Sony Music Entertainment (Japan) Inc.",
    "Date": 2012,
    "Disc Number": "1/1",
    "Genre": "J-Pop",
    "Title": "Rokutousei No Yoru",
    "Track Number": "12/13"
  },
  {
    "Album": "Sleepless Nights",
    "Album Artist": "Aimer",
    "Artist": "Aimer",
    "Copyright": "℗ 2012 Sony Music Entertainment (Japan) Inc.",
    "Date": 2012,
    "Disc Number": "1/1",
    "Genre": "J-Pop",
    "Title": "TWINKLE TWINKLE LITTLE STAR",
    "Track Number": "13/13"
  },
  {
    "Album": "SPARK-AGAIN",
    "Album Artist": "Aimer",
    "Artist": "Aimer",
    "Copyright": "℗ 2020 Sony Music Labels Inc.",
    "Date": 2020,
    "Disc Number": "1/1",
    "Genre": "J-Pop",
    "Title": "Kanashimi No Mukougawa",
    "Track Number": "1/3"
  },
  {
    "Album": "SPARK-AGAIN",
    "Album Artist": "Aimer",
    "Artist": "Aimer",
    "Copyright": "℗ 2020 Sony Music Labels Inc.",
    "Date": 2020,
    "Disc Number": "1/1",
    "Genre": "J-Pop",
    "Title": "Ash flame",
    "Track Number": "2/3"
  },
  {
    "Album": "SPARK-AGAIN",
    "Album Artist": "Aimer",
    "Artist": "Aimer",
    "Copyright": "℗ 2020 Sony Music Labels Inc.",
    "Date": 2020,
    "Disc Number": "1/1",
    "Genre": "J-Pop",
    "Title": "Work it out",
    "Track Number": "3/3"
  },
  {
    "Album": "StarRingChild",
    "Album Artist": "Aimer",
    "Artist": "Aimer",
    "Copyright": "℗ 2014 Sony Music Entertainment (Japan) Inc.",
    "Date": 2014,
    "Disc Number": "1/1",
    "Genre": "J-Pop",
    "Title": "Even Heaven",
    "Track Number": "1/2"
  },
  {
    "Album": "StarRingChild",
    "Album Artist": "Aimer",
    "Artist": "Aimer",
    "Copyright": "℗ 2014 Sony Music Entertainment (Japan) Inc.",
    "Date": 2014,
    "Disc Number": "1/1",
    "Genre": "J-Pop",
    "Title": "Mine",
    "Track Number": "2/2"
  },
  {
    "Album": "Sun Dance",
    "Album Artist": "Aimer",
    "Artist": "Aimer",
    "Copyright": "℗ 2017(2), 2018(7), 2019(1,3-6,8-10) SME Records",
    "Date": 2019,
    "Disc Number": "1/1",
    "Genre": "J-Pop",
    "Title": "soleil",
    "Track Number": "1/10"
  },
  {
    "Album": "Sun Dance",
    "Album Artist": "Aimer",
    "Artist": "Aimer",
    "Copyright": "℗ 2017(2), 2018(7), 2019(1,3-6,8-10) SME Records",
    "Date": 2019,
    "Disc Number": "1/1",
    "Genre": "J-Pop",
    "Title": "ONE",
    "Track Number": "2/10"
  },
  {
    "Album": "Sun Dance",
    "Album Artist": "Aimer",
    "Artist": "Aimer",
    "Copyright": "℗ 2017(2), 2018(7), 2019(1,3-6,8-10) SME Records",
    "Date": 2019,
    "Disc Number": "1/1",
    "Genre": "J-Pop",
    "Title": "We Two",
    "Track Number": "3/10"
  },
  {
    "Album": "Sun Dance",
    "Album Artist": "Aimer",
    "Artist": "Aimer",
    "Copyright": "℗ 2017(2), 2018(7), 2019(1,3-6,8-10) SME Records",
    "Date": 2019,
    "Disc Number": "1/1",
    "Genre": "J-Pop",
    "Title": "3min",
    "Track Number": "4/10"
  },
  {
    "Album": "Sun Dance",
    "Album Artist": "Aimer",
    "Artist": "Aimer",
    "Copyright": "℗ 2017(2), 2018(7), 2019(1,3-6,8-10) SME Records",
    "Date": 2019,
    "Disc Number": "1/1",
    "Genre": "J-Pop",
    "Title": "Koiwazurai",
    "Track Number": "5/10"
  },
  {
    "Album": "Sun Dance",
    "Album Artist": "Aimer",
    "Artist": "Aimer",
    "Copyright": "℗ 2017(2), 2018(7), 2019(1,3-6,8-10) SME Records",
    "Date": 2019,
    "Disc Number": "1/1",
    "Genre": "J-Pop",
    "Title": "Hanabiratachi No March",
    "Track Number": "6/10"
  },
  {
    "Album": "Sun Dance",
    "Album Artist": "Aimer",
    "Artist": "Aimer",
    "Copyright": "℗ 2017(2), 2018(7), 2019(1,3-6,8-10) SME Records",
    "Date": 2019,
    "Disc Number": "1/1",
    "Genre": "J-Pop",
    "Title": "Omoide Wa Kirei De",
    "Track Number": "7/10"
  },
  {
    "Album": "Sun Dance",
    "Album Artist": "Aimer",
    "Artist": "Aimer",
    "Copyright": "℗ 2017(2), 2018(7), 2019(1,3-6,8-10) SME Records",
    "Date": 2019,
    "Disc Number": "1/1",
    "Genre": "J-Pop",
    "Title": "Monochrome Syndrome",
    "Track Number": "8/10"
  },
  {
    "Album": "Sun Dance",
    "Album Artist": "Aimer",
    "Artist": "Aimer",
    "Copyright": "℗ 2017(2), 2018(7), 2019(1,3-6,8-10) SME Records",
    "Date": 2019,
    "Disc Number": "1/1",
    "Genre": "J-Pop",
    "Title": "SUN DANCE",
    "Track Number": "9/10"
  },
  {
    "Album": "Sun Dance",
    "Album Artist": "Aimer",
    "Artist": "Aimer",
    "Copyright": "℗ 2017(2), 2018(7), 2019(1,3-6,8-10) SME Records",
    "Date": 2019,
    "Disc Number": "1/1",
    "Genre": "J-Pop",
    "Title": "ONE -epilogue-",
    "Track Number": "10/10"
  },
  {
    "Album": "Torches",
    "Album Artist": "Aimer",
    "Artist": "Aimer",
    "Copyright": "℗ 2019 Sony Music Labels Inc.",
    "Date": 2019,
    "Disc Number": "1/1",
    "Genre": "J-Pop",
    "Title": "Blind to you",
    "Track Number": "1/4"
  },
  {
    "Album": "Torches",
    "Album Artist": "Aimer",
    "Artist": "Aimer",
    "Copyright": "℗ 2019 Sony Music Labels Inc.",
    "Date": 2019,
    "Disc Number": "1/1",
    "Genre": "J-Pop",
    "Title": "Daisy",
    "Track Number": "2/4"
  },
  {
    "Album": "Torches",
    "Album Artist": "Aimer",
    "Artist": "Aimer",
    "Copyright": "℗ 2019 Sony Music Labels Inc.",
    "Date": 2019,
    "Disc Number": "1/1",
    "Genre": "J-Pop",
    "Title": "Black Bird (Aimer \"soleil et pluie\" Asia Tour in Shanghai)",
    "Track Number": "3/4"
  },
  {
    "Album": "Torches",
    "Album Artist": "Aimer",
    "Artist": "Aimer",
    "Copyright": "℗ 2019 Sony Music Labels Inc.",
    "Date": 2019,
    "Disc Number": "1/1",
    "Genre": "J-Pop",
    "Title": "I beg you (Aimer \"soleil et pluie\" Asia Tour in Shanghai)",
    "Track Number": "4/4"
  },
  {
    "Album": "Walpurgis",
    "Album Artist": "Aimer",
    "Artist": "Aimer",
    "Copyright": "℗ 2020(6,9,13),2021(1,3-5,7,10-12,14) Sony Music Labels Inc. / 2019(2,8) Sony Music Entertainment (Japan) Inc.",
    "Date": 2021,
    "Disc Number": "1/1",
    "Genre": "J-Pop",
    "Title": "Walpurgis -prologue-",
    "Track Number": "1/14"
  },
  {
    "Album": "Walpurgis",
    "Album Artist": "Aimer",
    "Artist": "Aimer",
    "Copyright": "℗ 2019 Sony Music Labels Inc.",
    "Date": 2021,
    "Disc Number": "1/1",
    "Genre": "J-Pop",
    "Title": "STAND-ALONE",
    "Track Number": "2/14"
  },
  {
    "Album": "Walpurgis",
    "Album Artist": "Aimer",
    "Artist": "Aimer",
    "Copyright": "℗ 2020(6,9,13),2021(1,3-5,7,10-12,14) Sony Music Labels Inc. / 2019(2,8) Sony Music Entertainment (Japan) Inc.",
    "Date": 2021,
    "Disc Number": "1/1",
    "Genre": "J-Pop",
    "Title": "cold rain",
    "Track Number": "3/14"
  },
  {
    "Album": "Walpurgis",
    "Album Artist": "Aimer",
    "Artist": "Aimer",
    "Copyright": "℗ 2020(6,9,13),2021(1,3-5,7,10-12,14) Sony Music Labels Inc. / 2019(2,8) Sony Music Entertainment (Japan) Inc.",
    "Date": 2021,
    "Disc Number": "1/1",
    "Genre": "J-Pop",
    "Title": "Trill",
    "Track Number": "4/14"
  },
  {
    "Album": "Walpurgis",
    "Album Artist": "Aimer",
    "Artist": "Aimer with Vaundy",
    "Copyright": "℗ 2020(6,9,13),2021(1,3-5,7,10-12,14) Sony Music Labels Inc. / 2019(2,8) Sony Music Entertainment (Japan) Inc.",
    "Date": 2021,
    "Disc Number": "1/1",
    "Genre": "J-Pop",
    "Title": "Chikyuugi",
    "Track Number": "5/14"
  },
  {
    "Album": "Walpurgis",
    "Album Artist": "Aimer",
    "Artist": "Aimer",
    "Copyright": "℗ 2020 Sony Music Labels Inc.",
    "Date": 2021,
    "Disc Number": "1/1",
    "Genre": "J-Pop",
    "Title": "SPARK-AGAIN",
    "Track Number": "6/14"
  },
  {
    "Album": "Walpurgis",
    "Album Artist": "Aimer",
    "Artist": "Aimer",
    "Copyright": "℗ 2020(6,9,13),2021(1,3-5,7,10-12,14) Sony Music Labels Inc. / 2019(2,8) Sony Music Entertainment (Japan) Inc.",
    "Date": 2021,
    "Disc Number": "1/1",
    "Genre": "J-Pop",
    "Title": "wonderland",
    "Track Number": "7/14"
  },
  {
    "Album": "Walpurgis",
    "Album Artist": "Aimer",
    "Artist": "Aimer",
    "Copyright": "℗ 2019 Sony Music Labels Inc.",
    "Date": 2021,
    "Disc Number": "1/1",
    "Genre": "J-Pop",
    "Title": "Torches",
    "Track Number": "8/14"
  },
  {
    "Album": "Walpurgis",
    "Album Artist": "Aimer",
    "Artist": "Aimer",
    "Copyright": "℗ 2020 Sony Music Labels Inc.",
    "Date": 2021,
    "Disc Number": "1/1",
    "Genre": "J-Pop",
    "Title": "marie",
    "Track Number": "9/14"
  },
  {
    "Album": "Walpurgis",
    "Album Artist": "Aimer",
    "Artist": "Aimer",
    "Copyright": "℗ 2020(6,9,13),2021(1,3-5,7,10-12,14) Sony Music Labels Inc. / 2019(2,8) Sony Music Entertainment (Japan) Inc.",
    "Date": 2021,
    "Disc Number": "1/1",
    "Genre": "J-Pop",
    "Title": "ever after",
    "Track Number": "10/14"
  },
  {
    "Album": "Walpurgis",
    "Album Artist": "Aimer",
    "Artist": "Aimer",
    "Copyright": "℗ 2020(6,9,13),2021(1,3-5,7,10-12,14) Sony Music Labels Inc. / 2019(2,8) Sony Music Entertainment (Japan) Inc.",
    "Date": 2021,
    "Disc Number": "1/1",
    "Genre": "J-Pop",
    "Title": "hollow-mas",
    "Track Number": "11/14"
  },
  {
    "Album": "Walpurgis",
    "Album Artist": "Aimer",
    "Artist": "Aimer",
    "Copyright": "℗ 2020(6,9,13),2021(1,3-5,7,10-12,14) Sony Music Labels Inc. / 2019(2,8) Sony Music Entertainment (Japan) Inc.",
    "Date": 2021,
    "Disc Number": "1/1",
    "Genre": "J-Pop",
    "Title": "Kiro",
    "Track Number": "12/14"
  },
  {
    "Album": "Walpurgis",
    "Album Artist": "Aimer",
    "Artist": "Aimer",
    "Copyright": "℗ 2020 Sony Music Labels Inc.",
    "Date": 2021,
    "Disc Number": "1/1",
    "Genre": "J-Pop",
    "Title": "Haru Wa Yuku",
    "Track Number": "13/14"
  },
  {
    "Album": "Walpurgis",
    "Album Artist": "Aimer",
    "Artist": "Aimer",
    "Copyright": "℗ 2020(6,9,13),2021(1,3-5,7,10-12,14) Sony Music Labels Inc. / 2019(2,8) Sony Music Entertainment (Japan) Inc.",
    "Date": 2021,
    "Disc Number": "1/1",
    "Genre": "J-Pop",
    "Title": "Walpurgis",
    "Track Number": "14/14"
  }
]